odoo/addons/pos_payment_restriction/README.rst
odoo/addons/pos_payment_restriction/__init__.py
odoo/addons/pos_payment_restriction/__manifest__.py
odoo/addons/pos_payment_restriction/i18n/it.po
odoo/addons/pos_payment_restriction/i18n/pos_payment_restriction.pot
odoo/addons/pos_payment_restriction/models/__init__.py
odoo/addons/pos_payment_restriction/models/pos_config.py
odoo/addons/pos_payment_restriction/models/res_config_settings.py
odoo/addons/pos_payment_restriction/readme/CONTRIBUTORS.rst
odoo/addons/pos_payment_restriction/readme/DESCRIPTION.rst
odoo/addons/pos_payment_restriction/readme/HISTORY.rst
odoo/addons/pos_payment_restriction/readme/USAGE.rst
odoo/addons/pos_payment_restriction/static/description/icon.png
odoo/addons/pos_payment_restriction/static/description/index.html
odoo/addons/pos_payment_restriction/static/src/js/PaymentScreen.js
odoo/addons/pos_payment_restriction/views/pos_config.xml
odoo/addons/pos_payment_restriction/views/pos_payment_restriction.xml
odoo/addons/pos_payment_restriction/views/res_config_settings.xml
odoo_addon_pos_payment_restriction-16.0.1.0.0.4.dist-info/METADATA
odoo_addon_pos_payment_restriction-16.0.1.0.0.4.dist-info/WHEEL
odoo_addon_pos_payment_restriction-16.0.1.0.0.4.dist-info/top_level.txt
odoo_addon_pos_payment_restriction-16.0.1.0.0.4.dist-info/RECORD
