Metadata-Version: 2.1
Name: odoo-addon-pos_payment_restriction
Version: 16.0.1.0.0.4
Summary: Adds restrictions options on POS payment level
Home-page: https://github.com/OCA/pos
Author: ACSONE SA/NV,Odoo Community Association (OCA)
Author-email: support@odoo-community.org
License: AGPL-3
Classifier: Programming Language :: Python
Classifier: Framework :: Odoo
Classifier: Framework :: Odoo :: 16.0
Classifier: License :: OSI Approved :: GNU Affero General Public License v3
Classifier: Development Status :: 4 - Beta
Requires-Python: >=3.10
Requires-Dist: odoo <16.1dev,>=16.0a
